{"name":"Djminecraftgod","id":1568681,"alias":["Djminecraftgod"],"prefixi":[],"location":{"state":"TX","country":"United States"},"smash":{"slug":"user/db40ba81","url":"https://www.start.gg/user/db40ba81"},"auth":[],"private":false,"images":[],"tourneys":{"2017":[[],[],[]],"2018":[[],[],[]],"2019":[[],[],[]],"2020":[[],[],[]],"2021":[[],[],[]],"2022":[[{"data":{"main":{"wonAgainst":[{"name":"Buttons","seed":158}],"loss":[{"id":11342750,"name":"BM | Clem"},{"id":11452985,"name":"Wintqr"}],"lossPlacement":[25,97],"seed":227,"entity":11450691,"placement":129,"prizing":null},"sets":{"nodes":[{"createdAt":1666558729,"completedAt":1666560614,"startedAt":1666560307,"displayScore":"DQ","fullRoundText":"Losers Round 2","totalGames":5,"winnerId":11452985,"wPlacement":25,"lPlacement":33,"stream":null,"phaseGroup":{"displayIdentifier":"3","phase":{"name":"Bracket"}},"slots":[{"seed":{"placement":25,"seedNum":75},"standing":{"entrant":{"id":11452985,"name":"Wintqr","participants":[{"user":{"id":1261364},"player":{"id":1984640,"gamerTag":"Wintqr"}}]},"stats":{"score":{"value":0}}}},{"seed":{"placement":33,"seedNum":227},"standing":{"entrant":{"id":11450691,"name":"Djminecraftgod","participants":[{"user":{"id":1568681},"player":{"id":2389355,"gamerTag":"Djminecraftgod"}}]},"stats":{"score":{"value":-1}}}}],"games":null},{"createdAt":1666558729,"completedAt":1666559472,"startedAt":1666559172,"displayScore":"DQ","fullRoundText":"Losers Round 1","totalGames":5,"winnerId":11450691,"wPlacement":33,"lPlacement":49,"stream":null,"phaseGroup":{"displayIdentifier":"3","phase":{"name":"Bracket"}},"slots":[{"seed":{"placement":33,"seedNum":227},"standing":{"entrant":{"id":11450691,"name":"Djminecraftgod","participants":[{"user":{"id":1568681},"player":{"id":2389355,"gamerTag":"Djminecraftgod"}}]},"stats":{"score":{"value":-1}}}},{"seed":{"placement":49,"seedNum":158},"standing":{"entrant":{"id":11393951,"name":"Buttons","participants":[{"user":{"id":805078},"player":{"id":1278040,"gamerTag":"Buttons"}}]},"stats":{"score":{"value":-1}}}}],"games":null},{"createdAt":1666558729,"completedAt":1666559118,"startedAt":1666558832,"displayScore":"DQ","fullRoundText":"Winners Round 1","totalGames":5,"winnerId":11342750,"wPlacement":33,"lPlacement":49,"stream":null,"phaseGroup":{"displayIdentifier":"3","phase":{"name":"Bracket"}},"slots":[{"seed":{"placement":7,"seedNum":30},"standing":{"entrant":{"id":11342750,"name":"BM | Clem","participants":[{"user":{"id":1059791},"player":{"id":1731374,"gamerTag":"Clem"}}]},"stats":{"score":{"value":0}}}},{"seed":{"placement":33,"seedNum":227},"standing":{"entrant":{"id":11450691,"name":"Djminecraftgod","participants":[{"user":{"id":1568681},"player":{"id":2389355,"gamerTag":"Djminecraftgod"}}]},"stats":{"score":{"value":-1}}}}],"games":null}]}},"tourney_id":787780,"tourney_name":"Djminecraftgod","type":1}],[],[]]}}