{"name":"Troefred","id":1872485,"alias":["Troefred"],"prefixi":[],"location":{"state":"TX","country":"United States"},"smash":{"slug":"user/51286e41","url":"https://www.start.gg/user/51286e41"},"auth":[],"private":false,"images":[{"id":"4779856","type":"profile","url":"https://images.start.gg/images/user/1872485/image-d998a14c7f2dfa8bca89d804a4555009.png?ehk=ermJDcTj37OXXrPxuVK90S3XCtpot%2FF63ZyQ2RKz4pM%3D&ehkOptimized=mo3kgpkUmZpJ0Q4MFRtf2fJy9CmN9c%2Bh1IMbLZsMVgk%3D","__typename":"Image"}],"tourneys":{"2017":[[],[],[]],"2018":[[],[],[]],"2019":[[],[],[]],"2020":[[],[],[]],"2021":[[],[],[]],"2022":[[{"data":{"main":{"wonAgainst":[{"name":"Killoww","seed":275},{"name":"Bahn","seed":494}],"loss":[{"id":10295568,"name":"Kingdom | zyder"},{"id":10949795,"name":"Shadoww"}],"lossPlacement":[17,97],"seed":531,"entity":11472089,"placement":257,"prizing":0},"sets":{"nodes":[{"createdAt":1667568730,"completedAt":1667674047,"startedAt":1667673536,"displayScore":"Shadoww 2 - Troefred 0","fullRoundText":"Losers Round 3","totalGames":5,"winnerId":10949795,"wPlacement":7,"lPlacement":9,"stream":null,"phaseGroup":{"displayIdentifier":"C4","phase":{"name":"Phase 1 Pools"}},"slots":[{"seed":{"placement":4,"seedNum":46},"standing":{"entrant":{"id":10949795,"name":"Shadoww","participants":[{"user":{"id":229067},"player":{"id":337240,"gamerTag":"Shadoww"}}]},"stats":{"score":{"value":2}}}},{"seed":{"placement":9,"seedNum":531},"standing":{"entrant":{"id":11472089,"name":"Troefred","participants":[{"user":{"id":1872485},"player":{"id":2844438,"gamerTag":"Troefred"}}]},"stats":{"score":{"value":0}}}}],"games":null},{"createdAt":1667568730,"completedAt":1667672344,"startedAt":null,"displayScore":"DQ","fullRoundText":"Losers Round 2","totalGames":5,"winnerId":11472089,"wPlacement":9,"lPlacement":13,"stream":null,"phaseGroup":{"displayIdentifier":"C4","phase":{"name":"Phase 1 Pools"}},"slots":[{"seed":{"placement":13,"seedNum":275},"standing":{"entrant":{"id":10267018,"name":"Killoww","participants":[{"user":{"id":1857942},"player":{"id":2818398,"gamerTag":"Killoww"}}]},"stats":{"score":{"value":-1}}}},{"seed":{"placement":9,"seedNum":531},"standing":{"entrant":{"id":11472089,"name":"Troefred","participants":[{"user":{"id":1872485},"player":{"id":2844438,"gamerTag":"Troefred"}}]},"stats":{"score":{"value":0}}}}],"games":null},{"createdAt":1667568730,"completedAt":1667672294,"startedAt":1667671824,"displayScore":"Kingdom | zyder 2 - Troefred 0","fullRoundText":"Winners Round 2","totalGames":5,"winnerId":10295568,"wPlacement":9,"lPlacement":13,"stream":null,"phaseGroup":{"displayIdentifier":"C4","phase":{"name":"Phase 1 Pools"}},"slots":[{"seed":{"placement":3,"seedNum":19},"standing":{"entrant":{"id":10295568,"name":"Kingdom | zyder","participants":[{"user":{"id":371253},"player":{"id":524086,"gamerTag":"zyder"}}]},"stats":{"score":{"value":2}}}},{"seed":{"placement":9,"seedNum":531},"standing":{"entrant":{"id":11472089,"name":"Troefred","participants":[{"user":{"id":1872485},"player":{"id":2844438,"gamerTag":"Troefred"}}]},"stats":{"score":{"value":0}}}}],"games":null},{"createdAt":1667568730,"completedAt":1667671800,"startedAt":1667671142,"displayScore":"Bahn 0 - Troefred 2","fullRoundText":"Winners Round 1","totalGames":5,"winnerId":11472089,"wPlacement":13,"lPlacement":17,"stream":null,"phaseGroup":{"displayIdentifier":"C4","phase":{"name":"Phase 1 Pools"}},"slots":[{"seed":{"placement":17,"seedNum":494},"standing":{"entrant":{"id":11312718,"name":"Bahn","participants":[{"user":{"id":759661},"player":{"id":1199766,"gamerTag":"Bahn"}}]},"stats":{"score":{"value":0}}}},{"seed":{"placement":9,"seedNum":531},"standing":{"entrant":{"id":11472089,"name":"Troefred","participants":[{"user":{"id":1872485},"player":{"id":2844438,"gamerTag":"Troefred"}}]},"stats":{"score":{"value":2}}}}],"games":null}]}},"tourney_id":735870,"tourney_name":"Troefred","type":0}],[{"data":{"main":{"wonAgainst":[],"loss":[{"id":11113231,"name":"Roxtricity / NovaWaffles"},{"id":10826319,"name":"turbozack / Ija"}],"lossPlacement":[97,97],"seed":171,"entity":11481225,"placement":129,"prizing":null},"sets":{"nodes":[{"createdAt":1667503624,"completedAt":1667575063,"startedAt":1667574463,"displayScore":"turbozack / Ija 3 - Troefred / cannedfebreze 0","fullRoundText":"Losers Round 2","totalGames":5,"winnerId":10826319,"wPlacement":13,"lPlacement":17,"stream":null,"phaseGroup":{"displayIdentifier":"AA3","phase":{"name":"Phase 1 Pools"}},"slots":[{"seed":{"placement":13,"seedNum":123},"standing":{"entrant":{"id":10826319,"name":"turbozack / Ija","participants":[{"user":{"id":180776},"player":{"id":278715,"gamerTag":"turbozack"}},{"user":{"id":234930},"player":{"id":344654,"gamerTag":"Ija"}}]},"stats":{"score":{"value":3}}}},{"seed":{"placement":17,"seedNum":171},"standing":{"entrant":{"id":11481225,"name":"Troefred / cannedfebreze","participants":[{"user":{"id":1872485},"player":{"id":2844438,"gamerTag":"Troefred"}},{"user":{"id":2004002},"player":{"id":3088477,"gamerTag":"cannedfebreze"}}]},"stats":{"score":{"value":0}}}}],"games":null},{"createdAt":1667503624,"completedAt":1667573442,"startedAt":1667571718,"displayScore":"Roxtricity / NovaWaffles 3 - Troefred / cannedfebreze 1","fullRoundText":"Winners Round 1","totalGames":5,"winnerId":11113231,"wPlacement":17,"lPlacement":17,"stream":null,"phaseGroup":{"displayIdentifier":"AA3","phase":{"name":"Phase 1 Pools"}},"slots":[{"seed":{"placement":13,"seedNum":86},"standing":{"entrant":{"id":11113231,"name":"Roxtricity / NovaWaffles","participants":[{"user":{"id":1000538},"player":{"id":1633604,"gamerTag":"Roxtricity"}},{"user":{"id":1402827},"player":{"id":2159488,"gamerTag":"NovaWaffles"}}]},"stats":{"score":{"value":3}}}},{"seed":{"placement":17,"seedNum":171},"standing":{"entrant":{"id":11481225,"name":"Troefred / cannedfebreze","participants":[{"user":{"id":1872485},"player":{"id":2844438,"gamerTag":"Troefred"}},{"user":{"id":2004002},"player":{"id":3088477,"gamerTag":"cannedfebreze"}}]},"stats":{"score":{"value":1}}}}],"games":null}]}},"tourney_id":735873,"type":0,"tourney_name":"Troefred","team":{"teamname":"Troefred / cannedfebreze","teammate":{"id":2004002,"private":false,"name":"cannedfebreze","user":{"smash_id":2004002,"images":[{"id":"5184003","type":"profile","url":"https://images.start.gg/images/user/2004002/image-88b8e84a0ea1c92b22c827bbbcad2ffd.jpg?ehk=riyDTR%2B0FVKEKHQuFTzl3NdKQKBbthnEOSXZ6Nh9vgY%3D&ehkOptimized=jIroy6j87tP86pPm%2Ftbbd5uTSq27fKIUNer4eVCF%2FLk%3D","__typename":"Image"}],"url":"https://www.start.gg/user/cd585745","playerSlug":"user/cd585745"}}}}],[]]}}