{"name":"Soody","id":1876576,"alias":["Soody"],"prefixi":[],"location":{"state":null,"country":"United States"},"smash":{"slug":"user/3057bfa6","url":"https://www.start.gg/user/3057bfa6"},"auth":[{"platform":"DISCORD","username":"Soody#1016"}],"private":false,"images":[],"tourneys":{"2017":[[],[],[]],"2018":[[],[],[]],"2019":[[],[],[]],"2020":[[],[],[]],"2021":[[],[],[]],"2022":[[],[{"data":{"main":{"wonAgainst":[{"name":"Roxtricity / 34charlesoakley","seed":90}],"loss":[{"id":11456635,"name":"KingdomOfMagic / Chef Don"},{"id":11461465,"name":"Hyxbrid- / Cronus"}],"lossPlacement":[49,49],"seed":103,"entity":11507856,"placement":65,"prizing":null},"sets":{"nodes":[{"createdAt":1667077231,"completedAt":1667078471,"startedAt":1667078168,"displayScore":"DQ","fullRoundText":"Losers Round 2","totalGames":5,"winnerId":11461465,"wPlacement":25,"lPlacement":33,"stream":null,"phaseGroup":{"displayIdentifier":"2","phase":{"name":"Bracket"}},"slots":[{"seed":{"placement":25,"seedNum":51},"standing":{"entrant":{"id":11461465,"name":"Hyxbrid- / Cronus","participants":[{"user":{"id":1006903},"player":{"id":1645120,"gamerTag":"Hyxbrid-"}},{"user":{"id":1947086},"player":{"id":2990046,"gamerTag":"Cronus"}}]},"stats":{"score":{"value":-1}}}},{"seed":{"placement":33,"seedNum":103},"standing":{"entrant":{"id":11507856,"name":"Xsoulboundx2267 / Soody","participants":[{"user":{"id":1269767},"player":{"id":1995174,"gamerTag":"Xsoulboundx2267"}},{"user":{"id":1876576},"player":{"id":2855911,"gamerTag":"Soody"}}]},"stats":{"score":{"value":-1}}}}],"games":null},{"createdAt":1667077231,"completedAt":1667078056,"startedAt":1667077745,"displayScore":"DQ","fullRoundText":"Losers Round 1","totalGames":5,"winnerId":11507856,"wPlacement":33,"lPlacement":49,"stream":null,"phaseGroup":{"displayIdentifier":"2","phase":{"name":"Bracket"}},"slots":[{"seed":{"placement":33,"seedNum":103},"standing":{"entrant":{"id":11507856,"name":"Xsoulboundx2267 / Soody","participants":[{"user":{"id":1269767},"player":{"id":1995174,"gamerTag":"Xsoulboundx2267"}},{"user":{"id":1876576},"player":{"id":2855911,"gamerTag":"Soody"}}]},"stats":{"score":{"value":-1}}}},{"seed":{"placement":49,"seedNum":90},"standing":{"entrant":{"id":11462051,"name":"Roxtricity / 34charlesoakley","participants":[{"user":{"id":1000538},"player":{"id":1633604,"gamerTag":"Roxtricity"}},{"user":{"id":2002465},"player":{"id":3084989,"gamerTag":"34charlesoakley"}}]},"stats":{"score":{"value":-1}}}}],"games":null},{"createdAt":1667077231,"completedAt":1667077695,"startedAt":1667077234,"displayScore":"DQ","fullRoundText":"Winners Round 1","totalGames":5,"winnerId":11456635,"wPlacement":33,"lPlacement":49,"stream":null,"phaseGroup":{"displayIdentifier":"2","phase":{"name":"Bracket"}},"slots":[{"seed":{"placement":25,"seedNum":26},"standing":{"entrant":{"id":11456635,"name":"KingdomOfMagic / Chef Don","participants":[{"user":{"id":1196998},"player":{"id":1905007,"gamerTag":"Chef Don"}},{"user":{"id":1275027},"player":{"id":2002192,"gamerTag":"KingdomOfMagic"}}]},"stats":{"score":{"value":-1}}}},{"seed":{"placement":33,"seedNum":103},"standing":{"entrant":{"id":11507856,"name":"Xsoulboundx2267 / Soody","participants":[{"user":{"id":1269767},"player":{"id":1995174,"gamerTag":"Xsoulboundx2267"}},{"user":{"id":1876576},"player":{"id":2855911,"gamerTag":"Soody"}}]},"stats":{"score":{"value":-1}}}}],"games":null}]}},"tourney_id":787781,"tourney_name":"Soody","type":1,"team":{"teamname":"Xsoulboundx2267 / Soody","teammate":{"id":1269767,"private":false,"name":"Xsoulboundx2267","user":{"smash_id":1269767,"images":[{"id":"2839679","type":"profile","url":"https://images.start.gg/images/user/1269767/image-fd7b530909a9a98c16c43d2920f6c7df.png?ehk=3w5aMOQRSSDMm6Akme6QCqr14Vh%2FHAVWc%2F%2BG35G%2FJiQ%3D&ehkOptimized=A%2BrCWcQQiimmHvDKAONX5%2FQ%2Bwucbh8f0tFZW9HmVtQQ%3D","__typename":"Image"},{"id":"2839682","type":"banner","url":"https://images.start.gg/images/user/1269767/image-6753007d34c6059d236bf530658d4c2a.png?ehk=jfEyimJg0VKlJHE9BoFHYo0ISNFen2pVKlRbTx8nTvI%3D&ehkOptimized=h3Fp17yXjVO15q1K2Ecgi3%2FDo%2FqIZbVIdw7qn0FituY%3D","__typename":"Image"}],"url":"https://www.start.gg/user/6e47f868","playerSlug":"user/6e47f868"}}}}],[]]}}