{"name":"TFN_511","id":1973616,"alias":["TFN_511"],"prefixi":["TFN_511"],"location":{"state":null,"country":"Saudi Arabia"},"smash":{"slug":"user/d5c63318","url":"https://www.start.gg/user/d5c63318"},"auth":[],"private":false,"images":[],"tourneys":{"2017":[[],[],[]],"2018":[[],[],[]],"2019":[[],[],[]],"2020":[[],[],[]],"2021":[[],[],[]],"2022":[[],[],[{"data":{"main":{"wonAgainst":[{"name":"SZZ | Oszz","seed":71}],"loss":[{"id":11261324,"name":"ToledPedro"},{"id":11257332,"name":"xarope"}],"lossPlacement":[7,49],"seed":58,"entity":11205484,"placement":65,"prizing":null},"sets":{"nodes":[{"createdAt":1664571601,"completedAt":1664572936,"startedAt":1664572693,"displayScore":"DQ","fullRoundText":"Losers Round 2","totalGames":5,"winnerId":11257332,"wPlacement":13,"lPlacement":17,"stream":null,"phaseGroup":{"displayIdentifier":"2","phase":{"name":"Bracket"}},"slots":[{"seed":{"placement":17,"seedNum":58},"standing":{"entrant":{"id":11205484,"name":"TFN_511 | TFN_511","participants":[{"user":{"id":1973616},"player":{"id":3034553,"gamerTag":"TFN_511"}}]},"stats":{"score":{"value":-1}}}},{"seed":{"placement":13,"seedNum":18},"standing":{"entrant":{"id":11257332,"name":"xarope","participants":[{"user":{"id":1833912},"player":{"id":2769789,"gamerTag":"xarope"}}]},"stats":{"score":{"value":0}}}}],"games":null},{"createdAt":1664571601,"completedAt":1664572078,"startedAt":null,"displayScore":"DQ","fullRoundText":"Winners Round 2","totalGames":5,"winnerId":11261324,"wPlacement":9,"lPlacement":17,"stream":null,"phaseGroup":{"displayIdentifier":"2","phase":{"name":"Bracket"}},"slots":[{"seed":{"placement":3,"seedNum":7},"standing":{"entrant":{"id":11261324,"name":"ToledPedro","participants":[{"user":{"id":981943},"player":{"id":1600504,"gamerTag":"ToledPedro"}}]},"stats":{"score":{"value":0}}}},{"seed":{"placement":17,"seedNum":58},"standing":{"entrant":{"id":11205484,"name":"TFN_511 | TFN_511","participants":[{"user":{"id":1973616},"player":{"id":3034553,"gamerTag":"TFN_511"}}]},"stats":{"score":{"value":-1}}}}],"games":null},{"createdAt":1664571601,"completedAt":1664571601,"startedAt":null,"displayScore":"DQ","fullRoundText":"Winners Round 1","totalGames":5,"winnerId":11205484,"wPlacement":17,"lPlacement":17,"stream":null,"phaseGroup":{"displayIdentifier":"2","phase":{"name":"Bracket"}},"slots":[{"seed":{"placement":17,"seedNum":58},"standing":{"entrant":{"id":11205484,"name":"TFN_511 | TFN_511","participants":[{"user":{"id":1973616},"player":{"id":3034553,"gamerTag":"TFN_511"}}]},"stats":{"score":{"value":-1}}}},{"seed":{"placement":17,"seedNum":71},"standing":{"entrant":{"id":11209506,"name":"SZZ | Oszz","participants":[{"user":{"id":1961070},"player":{"id":3012601,"gamerTag":"Oszz"}}]},"stats":{"score":{"value":-1}}}}],"games":null}]}},"tourney_id":751044,"tourney_name":"TFN_511","type":1}]]}}