{"name":"addsky","id":1980101,"alias":["addsky"],"prefixi":["SOBR"],"location":{"state":null,"country":"Russia"},"smash":{"slug":"user/6d5ceae6","url":"https://www.start.gg/user/6d5ceae6"},"auth":[],"private":false,"images":[{"id":"5111629","type":"banner","url":"https://images.start.gg/images/user/1980101/image-c3c05e4d494115275a14bf3aa42bd354.png?ehk=t37%2B2Vv92dd4K2Snw1oMJY5KH1rJrYLti8Qg5TSioSs%3D&ehkOptimized=%2F8eZ9B%2BDe%2BYa1W3Wj6Qs4%2FR%2F1D9yZyJ2bez3RtQydiM%3D","__typename":"Image"},{"id":"5111642","type":"profile","url":"https://images.start.gg/images/user/1980101/image-d922a56f8c4ad311849c6e5179ccee81.jpg?ehk=dqVcG%2FmJ9GIxq9hn%2BUNxHd6SA7610h4KyV0sbGpLg1w%3D&ehkOptimized=mA82H8T%2BBy9PdMvUO2qPrn2MSOvX6dh5ABHtooVNT%2B4%3D","__typename":"Image"}],"tourneys":{"2017":[[],[],[]],"2018":[[],[],[]],"2019":[[],[],[]],"2020":[[],[],[]],"2021":[[],[],[]],"2022":[[],[],[{"data":{"main":{"wonAgainst":[],"loss":[{"id":11268626,"name":"Goofy / sage"},{"id":11216701,"name":"lil mevv / RC"}],"lossPlacement":[13,9],"seed":23,"entity":11260133,"placement":17,"prizing":null},"sets":{"nodes":[{"createdAt":1664643576,"completedAt":1664645842,"startedAt":1664645387,"displayScore":"lil mevv / RC 2 - s) / z) 0","fullRoundText":"Losers Round 1","totalGames":5,"winnerId":11216701,"wPlacement":13,"lPlacement":17,"stream":null,"phaseGroup":{"displayIdentifier":"1","phase":{"name":"Bracket"}},"slots":[{"seed":{"placement":9,"seedNum":4},"standing":{"entrant":{"id":11216701,"name":"lil mevv / RC","participants":[{"user":{"id":416352},"player":{"id":595602,"gamerTag":"RC"}},{"user":{"id":1422014},"player":{"id":2184022,"gamerTag":"lil mevv"}}]},"stats":{"score":{"value":2}}}},{"seed":{"placement":17,"seedNum":23},"standing":{"entrant":{"id":11260133,"name":"s) / z)","participants":[{"user":{"id":1980101},"player":{"id":3046002,"gamerTag":"addsky"}},{"user":{"id":1980102},"player":{"id":3046004,"gamerTag":"snitch"}}]},"stats":{"score":{"value":0}}}}],"games":[{"winnerId":11216701,"stage":null,"selections":null},{"winnerId":11216701,"stage":null,"selections":null}]},{"createdAt":1664643576,"completedAt":1664644364,"startedAt":1664643781,"displayScore":"Goofy / sage 2 - s) / z) 0","fullRoundText":"Winners Round 1","totalGames":5,"winnerId":11268626,"wPlacement":17,"lPlacement":17,"stream":null,"phaseGroup":{"displayIdentifier":"1","phase":{"name":"Bracket"}},"slots":[{"seed":{"placement":13,"seedNum":10},"standing":{"entrant":{"id":11268626,"name":"Goofy / sage","participants":[{"user":{"id":1621362},"player":{"id":2463458,"gamerTag":"sage"}},{"user":{"id":1750818},"player":{"id":2641270,"gamerTag":"Goofy"}}]},"stats":{"score":{"value":2}}}},{"seed":{"placement":17,"seedNum":23},"standing":{"entrant":{"id":11260133,"name":"s) / z)","participants":[{"user":{"id":1980101},"player":{"id":3046002,"gamerTag":"addsky"}},{"user":{"id":1980102},"player":{"id":3046004,"gamerTag":"snitch"}}]},"stats":{"score":{"value":0}}}}],"games":[{"winnerId":null,"stage":null,"selections":null},{"winnerId":11268626,"stage":null,"selections":null},{"winnerId":11268626,"stage":null,"selections":null}]}]}},"tourney_id":762150,"tourney_name":"addsky","type":1}]]}}