{"name":"brog","id":2007405,"alias":["brog"],"prefixi":["ganGreen"],"location":{"state":"OH","country":"United States"},"smash":{"slug":"user/0aef98a2","url":"https://www.start.gg/user/0aef98a2"},"auth":[],"private":false,"images":[],"tourneys":{"2017":[[],[],[]],"2018":[[],[],[]],"2019":[[],[],[]],"2020":[[],[],[]],"2021":[[],[],[]],"2022":[[{"data":{"main":{"wonAgainst":[],"loss":[{"id":10357174,"name":"Spaceatronix"},{"id":10330821,"name":"HOG | Vaxyle"}],"lossPlacement":[257,129],"seed":551,"entity":11561338,"placement":513,"prizing":0},"sets":{"nodes":[{"createdAt":1667568730,"completedAt":1667680403,"startedAt":null,"displayScore":"DQ","fullRoundText":"Losers Round 1","totalGames":5,"winnerId":10330821,"wPlacement":13,"lPlacement":17,"stream":null,"phaseGroup":{"displayIdentifier":"D2","phase":{"name":"Phase 1 Pools"}},"slots":[{"seed":{"placement":5,"seedNum":359},"standing":{"entrant":{"id":10330821,"name":"HOG | Vaxyle","participants":[{"user":{"id":1797309},"player":{"id":2707226,"gamerTag":"Vaxyle"}}]},"stats":{"score":{"value":0}}}},{"seed":{"placement":17,"seedNum":551},"standing":{"entrant":{"id":11561338,"name":"ganGreen | brog","participants":[{"user":{"id":2007405},"player":{"id":3096399,"gamerTag":"brog"}}]},"stats":{"score":{"value":-1}}}}],"games":null},{"createdAt":1667568730,"completedAt":1667679542,"startedAt":1667678769,"displayScore":"Spaceatronix 2 - ganGreen | brog 1","fullRoundText":"Winners Round 1","totalGames":5,"winnerId":10357174,"wPlacement":13,"lPlacement":17,"stream":null,"phaseGroup":{"displayIdentifier":"D2","phase":{"name":"Phase 1 Pools"}},"slots":[{"seed":{"placement":9,"seedNum":474},"standing":{"entrant":{"id":10357174,"name":"Spaceatronix","participants":[{"user":{"id":1141141},"player":{"id":1837286,"gamerTag":"Spaceatronix"}}]},"stats":{"score":{"value":2}}}},{"seed":{"placement":17,"seedNum":551},"standing":{"entrant":{"id":11561338,"name":"ganGreen | brog","participants":[{"user":{"id":2007405},"player":{"id":3096399,"gamerTag":"brog"}}]},"stats":{"score":{"value":1}}}}],"games":null}]}},"tourney_id":735870,"tourney_name":"brog","type":0}],[{"data":{"main":{"wonAgainst":[{"name":"Plubbor / beef","seed":149},{"name":"Zookilla / Starno","seed":188}],"loss":[{"id":11517091,"name":"hazN / eXoofed"},{"id":10959845,"name":"Kapp / Piggie"}],"lossPlacement":[49,33],"seed":197,"entity":11561343,"placement":97,"prizing":null},"sets":{"nodes":[{"createdAt":1667503624,"completedAt":1667577756,"startedAt":1667577492,"displayScore":"Kapp / Piggie 3 - GG | Flowey / brog 0","fullRoundText":"Losers Round 3","totalGames":5,"winnerId":10959845,"wPlacement":9,"lPlacement":13,"stream":null,"phaseGroup":{"displayIdentifier":"AA2","phase":{"name":"Phase 1 Pools"}},"slots":[{"seed":{"placement":5,"seedNum":44},"standing":{"entrant":{"id":10959845,"name":"Kapp / Piggie","participants":[{"user":{"id":1207723},"player":{"id":1918104,"gamerTag":"Piggie"}},{"user":{"id":1515584},"player":{"id":2312470,"gamerTag":"Kapp"}}]},"stats":{"score":{"value":3}}}},{"seed":{"placement":13,"seedNum":197},"standing":{"entrant":{"id":11561343,"name":"GG | Flowey / brog","participants":[{"user":{"id":1025094},"player":{"id":1676439,"gamerTag":"GG | Flowey"}},{"user":{"id":2007405},"player":{"id":3096399,"gamerTag":"brog"}}]},"stats":{"score":{"value":0}}}}],"games":null},{"createdAt":1667503624,"completedAt":1667575915,"startedAt":1667575226,"displayScore":"Plubbor / beef 0 - GG | Flowey / brog 3","fullRoundText":"Losers Round 2","totalGames":5,"winnerId":11561343,"wPlacement":13,"lPlacement":17,"stream":null,"phaseGroup":{"displayIdentifier":"AA2","phase":{"name":"Phase 1 Pools"}},"slots":[{"seed":{"placement":17,"seedNum":149},"standing":{"entrant":{"id":10357069,"name":"Plubbor / beef","participants":[{"user":{"id":1158657},"player":{"id":1858687,"gamerTag":"Plubbor"}},{"user":{"id":1874568},"player":{"id":2849683,"gamerTag":"beef"}}]},"stats":{"score":{"value":0}}}},{"seed":{"placement":13,"seedNum":197},"standing":{"entrant":{"id":11561343,"name":"GG | Flowey / brog","participants":[{"user":{"id":1025094},"player":{"id":1676439,"gamerTag":"GG | Flowey"}},{"user":{"id":2007405},"player":{"id":3096399,"gamerTag":"brog"}}]},"stats":{"score":{"value":3}}}}],"games":null},{"createdAt":1667503624,"completedAt":1667574106,"startedAt":1667574103,"displayScore":"DQ","fullRoundText":"Losers Round 1","totalGames":5,"winnerId":11561343,"wPlacement":17,"lPlacement":25,"stream":null,"phaseGroup":{"displayIdentifier":"AA2","phase":{"name":"Phase 1 Pools"}},"slots":[{"seed":{"placement":13,"seedNum":197},"standing":{"entrant":{"id":11561343,"name":"GG | Flowey / brog","participants":[{"user":{"id":1025094},"player":{"id":1676439,"gamerTag":"GG | Flowey"}},{"user":{"id":2007405},"player":{"id":3096399,"gamerTag":"brog"}}]},"stats":{"score":{"value":0}}}},{"seed":{"placement":25,"seedNum":188},"standing":{"entrant":{"id":11542332,"name":"Zookilla / Starno","participants":[{"user":{"id":586309},"player":{"id":919770,"gamerTag":"Starno"}},{"user":{"id":1052304},"player":{"id":1721976,"gamerTag":"Zookilla"}}]},"stats":{"score":{"value":-1}}}}],"games":null},{"createdAt":1667503624,"completedAt":1667572606,"startedAt":1667571811,"displayScore":"hazN / eXoofed 3 - GG | Flowey / brog 0","fullRoundText":"Winners Round 1","totalGames":5,"winnerId":11517091,"wPlacement":17,"lPlacement":25,"stream":null,"phaseGroup":{"displayIdentifier":"AA2","phase":{"name":"Phase 1 Pools"}},"slots":[{"seed":{"placement":7,"seedNum":60},"standing":{"entrant":{"id":11517091,"name":"hazN / eXoofed","participants":[{"user":{"id":180302},"player":{"id":278421,"gamerTag":"hazN"}},{"user":{"id":211690},"player":{"id":312046,"gamerTag":"eXoofed"}}]},"stats":{"score":{"value":3}}}},{"seed":{"placement":13,"seedNum":197},"standing":{"entrant":{"id":11561343,"name":"GG | Flowey / brog","participants":[{"user":{"id":1025094},"player":{"id":1676439,"gamerTag":"GG | Flowey"}},{"user":{"id":2007405},"player":{"id":3096399,"gamerTag":"brog"}}]},"stats":{"score":{"value":0}}}}],"games":null}]}},"tourney_id":735873,"type":0,"tourney_name":"brog","team":{"teamname":"GG | Flowey / brog","teammate":{"id":1025094,"private":false,"name":"GG | Flowey","user":{"smash_id":1025094,"images":[],"url":"https://www.start.gg/user/36e9ba29","playerSlug":"user/36e9ba29"}}}}],[]]}}