{"name":"Aserpant","id":2008332,"alias":["Aserpant","Zoinks"],"prefixi":[],"location":{"state":"ON","country":"Canada"},"smash":{"slug":"user/4b04a1da","url":"https://www.start.gg/user/4b04a1da"},"auth":[{"platform":"DISCORD","username":"Aserpant#1530"}],"private":false,"images":[],"tourneys":{"2017":[[],[],[]],"2018":[[],[],[]],"2019":[[],[],[]],"2020":[[],[],[]],"2021":[[],[],[]],"2022":[[],[{"data":{"main":{"wonAgainst":[{"name":"animefan1266 / dawg","seed":1},{"name":"Jãozin / Darkas","seed":21},{"name":"notswiftylol / 30fps BTW","seed":48}],"loss":[{"id":11531535,"name":"Axel / shotgun"},{"id":11527981,"name":"rusted / Wobby"}],"lossPlacement":[2,13],"seed":44,"entity":11527726,"placement":17,"prizing":null},"sets":{"nodes":[{"createdAt":1667166765,"completedAt":1667169851,"startedAt":1667169120,"displayScore":"rusted / Wobby 3 - Bravo / Aserpant 0","fullRoundText":"Losers Round 2","totalGames":5,"winnerId":11527981,"wPlacement":13,"lPlacement":17,"stream":null,"phaseGroup":{"displayIdentifier":"1","phase":{"name":"Top 32"}},"slots":[{"seed":{"placement":13,"seedNum":2},"standing":{"entrant":{"id":11527981,"name":"rusted / Wobby","participants":[{"user":{"id":1674849},"player":{"id":2547135,"gamerTag":"Wobby"}},{"user":{"id":1782559},"player":{"id":2683301,"gamerTag":"rusted"}}]},"stats":{"score":{"value":3}}}},{"seed":{"placement":17,"seedNum":21},"standing":{"entrant":{"id":11527726,"name":"Bravo / Aserpant","participants":[{"user":{"id":2008333},"player":{"id":3098835,"gamerTag":"Bravo"}},{"user":{"id":2008332},"player":{"id":3098836,"gamerTag":"Aserpant"}}]},"stats":{"score":{"value":0}}}}],"games":[{"winnerId":11527981,"stage":null,"selections":null},{"winnerId":11527981,"stage":null,"selections":null},{"winnerId":11527981,"stage":null,"selections":null}]},{"createdAt":1667166765,"completedAt":1667169015,"startedAt":1667167826,"displayScore":"notswiftylol / 30fps BTW 0 - Bravo / Aserpant 3","fullRoundText":"Losers Round 1","totalGames":5,"winnerId":11527726,"wPlacement":17,"lPlacement":25,"stream":null,"phaseGroup":{"displayIdentifier":"1","phase":{"name":"Top 32"}},"slots":[{"seed":{"placement":25,"seedNum":28},"standing":{"entrant":{"id":11522674,"name":"notswiftylol / 30fps BTW","participants":[{"user":{"id":1932310},"player":{"id":2968144,"gamerTag":"notswiftylol"}},{"user":{"id":2007891},"player":{"id":3097538,"gamerTag":"30fps BTW"}}]},"stats":{"score":{"value":0}}}},{"seed":{"placement":17,"seedNum":21},"standing":{"entrant":{"id":11527726,"name":"Bravo / Aserpant","participants":[{"user":{"id":2008333},"player":{"id":3098835,"gamerTag":"Bravo"}},{"user":{"id":2008332},"player":{"id":3098836,"gamerTag":"Aserpant"}}]},"stats":{"score":{"value":3}}}}],"games":[{"winnerId":11527726,"stage":null,"selections":null},{"winnerId":11527726,"stage":null,"selections":null},{"winnerId":11527726,"stage":null,"selections":null}]},{"createdAt":1667164785,"completedAt":1667166073,"startedAt":1667165722,"displayScore":"DQ","fullRoundText":"Losers Round 2","totalGames":5,"winnerId":11527726,"wPlacement":13,"lPlacement":17,"stream":null,"phaseGroup":{"displayIdentifier":"1","phase":{"name":"Bracket"}},"slots":[{"seed":{"placement":9,"seedNum":44},"standing":{"entrant":{"id":11527726,"name":"Bravo / Aserpant","participants":[{"user":{"id":2008333},"player":{"id":3098835,"gamerTag":"Bravo"}},{"user":{"id":2008332},"player":{"id":3098836,"gamerTag":"Aserpant"}}]},"stats":{"score":{"value":0}}}},{"seed":{"placement":17,"seedNum":1},"standing":{"entrant":{"id":11452128,"name":"animefan1266 / dawg","participants":[{"user":{"id":661805},"player":{"id":1050211,"gamerTag":"animefan1266"}},{"user":{"id":668992},"player":{"id":1059364,"gamerTag":"dawg"}}]},"stats":{"score":{"value":-1}}}}],"games":null},{"createdAt":1667164785,"completedAt":1667165667,"startedAt":1667165202,"displayScore":"Axel / shotgun 2 - Bravo / Aserpant 0","fullRoundText":"Winners Round 2","totalGames":5,"winnerId":11531535,"wPlacement":9,"lPlacement":17,"stream":null,"phaseGroup":{"displayIdentifier":"1","phase":{"name":"Bracket"}},"slots":[{"seed":{"placement":7,"seedNum":12},"standing":{"entrant":{"id":11531535,"name":"Axel / shotgun","participants":[{"user":{"id":1466305},"player":{"id":2245583,"gamerTag":"shotgun"}},{"user":{"id":1946848},"player":{"id":2989713,"gamerTag":"Axel"}}]},"stats":{"score":{"value":2}}}},{"seed":{"placement":9,"seedNum":44},"standing":{"entrant":{"id":11527726,"name":"Bravo / Aserpant","participants":[{"user":{"id":2008333},"player":{"id":3098835,"gamerTag":"Bravo"}},{"user":{"id":2008332},"player":{"id":3098836,"gamerTag":"Aserpant"}}]},"stats":{"score":{"value":0}}}}],"games":[{"winnerId":11531535,"stage":null,"selections":null},{"winnerId":11531535,"stage":null,"selections":null}]},{"createdAt":1667164785,"completedAt":1667165178,"startedAt":1667164788,"displayScore":"DQ","fullRoundText":"Winners Round 1","totalGames":5,"winnerId":11527726,"wPlacement":17,"lPlacement":25,"stream":null,"phaseGroup":{"displayIdentifier":"1","phase":{"name":"Bracket"}},"slots":[{"seed":{"placement":25,"seedNum":21},"standing":{"entrant":{"id":10891270,"name":"Jãozin / Darkas","participants":[{"user":{"id":1191352},"player":{"id":1898547,"gamerTag":"Darkas"}},{"user":{"id":1249311},"player":{"id":1968076,"gamerTag":"Jãozin"}}]},"stats":{"score":{"value":-1}}}},{"seed":{"placement":9,"seedNum":44},"standing":{"entrant":{"id":11527726,"name":"Bravo / Aserpant","participants":[{"user":{"id":2008333},"player":{"id":3098835,"gamerTag":"Bravo"}},{"user":{"id":2008332},"player":{"id":3098836,"gamerTag":"Aserpant"}}]},"stats":{"score":{"value":0}}}}],"games":null}]}},"tourney_id":765801,"tourney_name":"Aserpant","type":1,"team":{"teamname":"Bravo / Aserpant","teammate":{"id":2008333,"private":false,"name":"Bravo","user":{"smash_id":2008333,"images":[],"url":"https://www.start.gg/user/b25b47c7","playerSlug":"user/b25b47c7"}}}}],[]]}}